README.rst
setup.py
tdxutil/__init__.py
tdxutil/collections.py
tdxutil/data.py
tdxutil/exceptions.py
tdxutil/validation.py
tdxutil/version.py
tdxutil.egg-info/PKG-INFO
tdxutil.egg-info/SOURCES.txt
tdxutil.egg-info/dependency_links.txt
tdxutil.egg-info/not-zip-safe
tdxutil.egg-info/requires.txt
tdxutil.egg-info/top_level.txt