Metadata-Version: 1.1
Name: tdxutil
Version: 0.0.6
Summary: Tools for working with container types, command data operations, and concise exception handling
Home-page: https://github.com/stroxler/tdxutil
Author: Steven Troxler
Author-email: steven.troxler@gmail.com
License: MIT
Platform: UNKNOWN
Classifier: Development Status :: 3 - Alpha
Classifier: License :: OSI Approved :: MIT License
Classifier: Programming Language :: Python :: 2.7
